{
	"name": "AzureSqlTableEmpDtl",
	"properties": {
		"linkedServiceName": {
			"referenceName": "AzureSqlDatabaseLS",
			"type": "LinkedServiceReference"
		},
		"annotations": [],
		"type": "AzureSqlTable",
		"schema": [
			{
				"name": "empid",
				"type": "int",
				"precision": 10
			},
			{
				"name": "empname",
				"type": "varchar"
			},
			{
				"name": "skills",
				"type": "nvarchar"
			},
			{
				"name": "address",
				"type": "nvarchar"
			}
		],
		"typeProperties": {
			"schema": "dbo",
			"table": "emp_dtl"
		}
	}
}